

{
  "sampleStocks" : [

      [{
        "id" : "aapl" ,
        "symbol" :"AAPL",
        "sector" : "electronictechnology",
        "securityType" : "cs",
        "bidPrice" : 176.93,
        "bidSize" : 100,
        "askPrice" : 176.95,
        "askSize" : 100,
        "lastUpdated" : 1551714139337,
        "lastSalePrice" : 176.94,
        "lastSaleSize" : 600,
        "lastSaleTime" : 1551714136836,
        "volume" : 234434
      }],
      [{
        "id" : "amzn",
        "symbol" :"AMZN",
        "sector" : "electronictechnology",
        "securityType" : "cs",
        "bidPrice" : 1100.93,
        "bidSize" : 100,
        "askPrice" : 176.95,
        "askSize" : 100,
        "lastUpdated" : 1551714139337,
        "lastSalePrice" : 176.94,
        "lastSaleSize" : 600,
        "lastSaleTime" : 1551714136836,
        "volume" : 234434
      }],
      [{
        "id" : "boa",
        "symbol" :"boa",
        "sector" : "electronictechnology",
        "securityType" : "cs",
        "bidPrice" : 54.93,
        "bidSize" : 100,
        "askPrice" : 176.95,
        "askSize" : 100,
        "lastUpdated" : 1551714139337,
        "lastSalePrice" : 176.94,
        "lastSaleSize" : 600,
        "lastSaleTime" : 1551714136836,
        "volume" : 234434
      }],
      [{
        "id" : "SNAP",
        "symbol" :"SNAP",
        "sector" : "electronictechnology",
        "securityType" : "cs",
        "bidPrice" : 28.13,
        "bidSize" : 100,
        "askPrice" : 176.95,
        "askSize" : 100,
        "lastUpdated" : 1551714139337,
        "lastSalePrice" : 176.94,
        "lastSaleSize" : 600,
        "lastSaleTime" : 1551714136836,
        "volume" : 234434
      }],
      [{
        "id" : "BRK.B",
        "symbol" :"BRK.B",
        "sector" : "electronictechnology",
        "securityType" : "cs",
        "bidPrice" : 54.93,
        "bidSize" : 100,
        "askPrice" : 176.95,
        "askSize" : 100,
        "lastUpdated" : 1551714139337,
        "lastSalePrice" : 176.94,
        "lastSaleSize" : 600,
        "lastSaleTime" : 1551714136836,
        "volume" : 234434
      }],
      [{
        "id" : "baba",
        "symbol" :"baba",
        "sector" : "electronictechnology",
        "securityType" : "cs",
        "bidPrice" : 54.93,
        "bidSize" : 100,
        "askPrice" : 176.95,
        "askSize" : 100,
        "lastUpdated" : 1551714139337,
        "lastSalePrice" : 176.94,
        "lastSaleSize" : 600,
        "lastSaleTime" : 1551714136836,
        "volume" : 234434
      }],
      [{
        "id" : "fb",
        "symbol" :"fb",
        "sector" : "electronictechnology",
        "securityType" : "cs",
        "bidPrice" : 54.93,
        "bidSize" : 100,
        "askPrice" : 176.95,
        "askSize" : 100,
        "lastUpdated" : 1551714139337,
        "lastSalePrice" : 176.94,
        "lastSaleSize" : 600,
        "lastSaleTime" : 1551714136836,
        "volume" : 234434
      }],
      [{
        "id" : "adbe",
        "symbol" :"adbe",
        "sector" : "electronictechnology",
        "securityType" : "cs",
        "bidPrice" : 54.93,
        "bidSize" : 100,
        "askPrice" : 176.95,
        "askSize" : 100,
        "lastUpdated" : 1551714139337,
        "lastSalePrice" : 176.94,
        "lastSaleSize" : 600,
        "lastSaleTime" : 1551714136836,
        "volume" : 234434
      }],
      [{
        "id" : "JPM",
        "symbol" :"JPM",
        "sector" : "electronictechnology",
        "securityType" : "cs",
        "bidPrice" : 54.93,
        "bidSize" : 100,
        "askPrice" : 176.95,
        "askSize" : 100,
        "lastUpdated" : 1551714139337,
        "lastSalePrice" : 176.94,
        "lastSaleSize" : 600,
        "lastSaleTime" : 1551714136836,
        "volume" : 234434
      }],
      [{
        "id" : "F",
        "symbol" :"F",
        "sector" : "electronictechnology",
        "securityType" : "cs",
        "bidPrice" : 54.93,
        "bidSize" : 100,
        "askPrice" : 176.95,
        "askSize" : 100,
        "lastUpdated" : 1551714139337,
        "lastSalePrice" : 176.94,
        "lastSaleSize" : 600,
        "lastSaleTime" : 1551714136836,
        "volume" : 234434
      }],
      [{
        "id" : "T",
        "symbol" :"T",
        "sector" : "electronictechnology",
        "securityType" : "cs",
        "bidPrice" : 54.93,
        "bidSize" : 100,
        "askPrice" : 176.95,
        "askSize" : 100,
        "lastUpdated" : 1551714139337,
        "lastSalePrice" : 176.94,
        "lastSaleSize" : 600,
        "lastSaleTime" : 1551714136836,
        "volume" : 234434
      }]
    ]
}
